docker/Dockerfile
docker/build.sh
fs_synapse-2.1.0.dist-info/licenses/LICENSE.txt
synapsefs/__init__.py
synapsefs/open_parent_fs.py
synapsefs/opener.py
synapsefs/remote_file.py
synapsefs/synapsefs.py
fs_synapse-2.1.0.dist-info/METADATA
fs_synapse-2.1.0.dist-info/WHEEL
fs_synapse-2.1.0.dist-info/entry_points.txt
fs_synapse-2.1.0.dist-info/top_level.txt
fs_synapse-2.1.0.dist-info/RECORD
