Metadata-Version: 2.4
Name: fs-synapse
Version: 2.1.0
Summary: A Synapse implementation of the PyFileSystem2 interface
Home-page: https://github.com/sage-Bionetworks/fs-synapse
Author: Bruno Grande
Author-email: bruno.grande@sagebase.org
License: Apache-2.0
Project-URL: Source, https://github.com/sage-Bionetworks/fs-synapse
Platform: any
Classifier: Development Status :: 4 - Beta
Classifier: Programming Language :: Python
Requires-Python: <3.12,>=3.9
License-File: LICENSE.txt
Requires-Dist: fs~=2.4
Requires-Dist: synapseclient<5,>=4.7.0
Provides-Extra: testing
Requires-Dist: setuptools~=65.0; extra == "testing"
Requires-Dist: pytest~=7.0; extra == "testing"
Requires-Dist: pytest-cov~=4.0; extra == "testing"
Requires-Dist: pytest-mock~=3.0; extra == "testing"
Requires-Dist: hypothesis~=4.0; extra == "testing"
Requires-Dist: nbmake~=1.3; extra == "testing"
Requires-Dist: pytest-xdist<3.0.0,>=2.2; extra == "testing"
Provides-Extra: dev
Requires-Dist: pre-commit~=2.0; extra == "dev"
Requires-Dist: tox~=3.0; extra == "dev"
Requires-Dist: sphinx-rtd-theme~=1.0; extra == "dev"
Requires-Dist: black~=22.0; extra == "dev"
Requires-Dist: flake8~=5.0; extra == "dev"
Requires-Dist: isort~=5.0; extra == "dev"
Requires-Dist: mypy~=0.9; extra == "dev"
Requires-Dist: flake8-pyproject~=1.0; extra == "dev"
Requires-Dist: sphinx-autodoc-typehints~=1.21; extra == "dev"
Requires-Dist: interrogate~=1.6; extra == "dev"
Dynamic: license-file
